{
  "$id": "#/properties/PersonVerified",
  "type": "object",
  "title": "The PersonVerified Schema",
  "required": [
    "personId"
  ],
  "additionalProperties": false,
  "properties": {
    "personId": {
      "$id": "#/properties/personId",
      "type": "string",
      "title": "personId"
    },
    "NameVerified": {
      "$id": "#/properties/nameVerified",
      "type": "boolean",
      "title": "Name"
    },
    "PhonenameVerified": {
      "$id": "#/properties/phonenameVerified",
      "type": "boolean",
      "title": "phone"
    },
    "TeacherIdnameVerified": {
      "$id": "#/properties/teacherIdnameVerified",
      "type": "boolean",
      "title": "Teacher Id"
    },
    "SchoolnameVerified": {
      "$id": "#/properties/schoolnameVerified",
      "type": "boolean",
      "title": "school"
    }
  }
}
